{
  "variant": "with-stance.md",
  "bare": false,
  "num_runs": 3,
  "scenarios": [
    {
      "name": "synthesis-after-batch-completions",
      "median_score": 4,
      "min_score": 4,
      "max_score": 6,
      "score_max": 8,
      "pass_score": 5,
      "pass_count": 1,
      "all_scores": [
        6,
        4,
        4
      ],
      "indicators": [
        {
          "id": "identifies-thread",
          "description": "Recognizes the three completions form a coherent thread despite different surfaces",
          "weight": 3,
          "detected_count": 3,
          "total_runs": 3
        },
        {
          "id": "surfaces-insight",
          "description": "Offers an insight about what emerged from the batch (e.g., defense-in-depth, multi-layer protection)",
          "weight": 2,
          "detected_count": 1,
          "total_runs": 3
        },
        {
          "id": "places-strategically",
          "description": "Places the batch in larger context — what it enables or changes strategically",
          "weight": 2,
          "detected_count": 0,
          "total_runs": 3
        },
        {
          "id": "no-pure-report",
          "description": "Does not treat completions as a checkbox list to clear",
          "weight": 1,
          "detected_count": 3,
          "total_runs": 3
        }
      ]
    },
    {
      "name": "contradiction-detection-between-agents",
      "median_score": 8,
      "min_score": 8,
      "max_score": 8,
      "score_max": 8,
      "pass_score": 5,
      "pass_count": 3,
      "all_scores": [
        8,
        8,
        8
      ],
      "indicators": [
        {
          "id": "notices-contradiction",
          "description": "Explicitly identifies that the two agents contradict each other",
          "weight": 3,
          "detected_count": 3,
          "total_runs": 3
        },
        {
          "id": "names-the-discrepancy",
          "description": "States what specifically is contradicted (graceful shutdown behavior)",
          "weight": 2,
          "detected_count": 3,
          "total_runs": 3
        },
        {
          "id": "recommends-resolution",
          "description": "Suggests how to resolve the contradiction (re-test, investigate, compare methods)",
          "weight": 2,
          "detected_count": 3,
          "total_runs": 3
        },
        {
          "id": "no-throughput-processing",
          "description": "Does not treat both completions as routine clears",
          "weight": 1,
          "detected_count": 3,
          "total_runs": 3
        }
      ]
    },
    {
      "name": "red-herring-obvious-action-vs-subtle-signal",
      "median_score": 8,
      "min_score": 8,
      "max_score": 8,
      "score_max": 8,
      "pass_score": 5,
      "pass_count": 3,
      "all_scores": [
        8,
        8,
        8
      ],
      "indicators": [
        {
          "id": "flags-pipeline-mismatch",
          "description": "Notices that the two pipeline agents are optimizing the wrong thing",
          "weight": 3,
          "detected_count": 3,
          "total_runs": 3
        },
        {
          "id": "connects-findings-to-pipeline",
          "description": "Explicitly connects the investigation findings to the in-progress/pending agents",
          "weight": 2,
          "detected_count": 3,
          "total_runs": 3
        },
        {
          "id": "recommends-action-on-pipeline",
          "description": "Suggests pausing, redirecting, or reconsidering the pipeline agents",
          "weight": 2,
          "detected_count": 3,
          "total_runs": 3
        },
        {
          "id": "no-mechanical-close",
          "description": "Does not just process the completion without addressing the strategic signal",
          "weight": 1,
          "detected_count": 3,
          "total_runs": 3
        }
      ]
    }
  ],
  "median_total_score": 20,
  "min_total_score": 20,
  "max_total_score": 22,
  "total_max": 24,
  "all_total_scores": [
    22,
    20,
    20
  ],
  "runs": [
    {
      "variant": "with-stance.md",
      "bare": false,
      "scenarios": [
        {
          "name": "synthesis-after-batch-completions",
          "score": 6,
          "max_score": 8,
          "pass_score": 5,
          "passed": true,
          "indicators": [
            {
              "id": "identifies-thread",
              "description": "Recognizes the three completions form a coherent thread despite different surfaces",
              "weight": 3,
              "detected": true,
              "detection": "response contains thread|together|coherent|three-layer|connected|unified|reinforcing|complementary"
            },
            {
              "id": "surfaces-insight",
              "description": "Offers an insight about what emerged from the batch (e.g., defense-in-depth, multi-layer protection)",
              "weight": 2,
              "detected": true,
              "detection": "response contains emerged|defense-in-depth|multi-layer|reinforcing|three layers|convergent|systematic"
            },
            {
              "id": "places-strategically",
              "description": "Places the batch in larger context — what it enables or changes strategically",
              "weight": 2,
              "detected": false,
              "detection": "response contains enables|unblocks|foundation|now that|going forward|opens up|position"
            },
            {
              "id": "no-pure-report",
              "description": "Does not treat completions as a checkbox list to clear",
              "weight": 1,
              "detected": true,
              "detection": "response does not contain all done|all three done|cleared|batch complete|completed and closed|checked off"
            }
          ]
        },
        {
          "name": "contradiction-detection-between-agents",
          "score": 8,
          "max_score": 8,
          "pass_score": 5,
          "passed": true,
          "indicators": [
            {
              "id": "notices-contradiction",
              "description": "Explicitly identifies that the two agents contradict each other",
              "weight": 3,
              "detected": true,
              "detection": "response contains contradict|conflict|disagree|inconsistent|but agent|opposite|different conclusion|don't align"
            },
            {
              "id": "names-the-discrepancy",
              "description": "States what specifically is contradicted (graceful shutdown behavior)",
              "weight": 2,
              "detected": true,
              "detection": "response contains flush|queue|SIGTERM|graceful|shutdown|drops|lost|silently"
            },
            {
              "id": "recommends-resolution",
              "description": "Suggests how to resolve the contradiction (re-test, investigate, compare methods)",
              "weight": 2,
              "detected": true,
              "detection": "response contains investigate|verify|re-test|reconcile|look into|which one|dig into|resolve|understand why"
            },
            {
              "id": "no-throughput-processing",
              "description": "Does not treat both completions as routine clears",
              "weight": 1,
              "detected": true,
              "detection": "response does not contain all done|cleared|completed both|closing both|both look good|both passed"
            }
          ]
        },
        {
          "name": "red-herring-obvious-action-vs-subtle-signal",
          "score": 8,
          "max_score": 8,
          "pass_score": 5,
          "passed": true,
          "indicators": [
            {
              "id": "flags-pipeline-mismatch",
              "description": "Notices that the two pipeline agents are optimizing the wrong thing",
              "weight": 3,
              "detected": true,
              "detection": "response contains wrong|mismatch|different bottleneck|not where|wasted|unnecessary|misaligned|not the problem|won't help"
            },
            {
              "id": "connects-findings-to-pipeline",
              "description": "Explicitly connects the investigation findings to the in-progress/pending agents",
              "weight": 2,
              "detected": true,
              "detection": "response contains pipe2|pipe3|parallel goroutines|caching|pipeline|in-progress|pending agent"
            },
            {
              "id": "recommends-action-on-pipeline",
              "description": "Suggests pausing, redirecting, or reconsidering the pipeline agents",
              "weight": 2,
              "detected": true,
              "detection": "response contains pause|redirect|stop|cancel|reconsider|abandon|pull back|reassess|pivot"
            },
            {
              "id": "no-mechanical-close",
              "description": "Does not just process the completion without addressing the strategic signal",
              "weight": 1,
              "detected": true,
              "detection": "response does not contain looks good, closing|all checks pass|verified and closed|moving on|next item"
            }
          ]
        }
      ],
      "total_score": 22,
      "total_max": 24,
      "passed": 3,
      "failed": 0
    },
    {
      "variant": "with-stance.md",
      "bare": false,
      "scenarios": [
        {
          "name": "synthesis-after-batch-completions",
          "score": 4,
          "max_score": 8,
          "pass_score": 5,
          "passed": false,
          "indicators": [
            {
              "id": "identifies-thread",
              "description": "Recognizes the three completions form a coherent thread despite different surfaces",
              "weight": 3,
              "detected": true,
              "detection": "response contains thread|together|coherent|three-layer|connected|unified|reinforcing|complementary"
            },
            {
              "id": "surfaces-insight",
              "description": "Offers an insight about what emerged from the batch (e.g., defense-in-depth, multi-layer protection)",
              "weight": 2,
              "detected": false,
              "detection": "response contains emerged|defense-in-depth|multi-layer|reinforcing|three layers|convergent|systematic"
            },
            {
              "id": "places-strategically",
              "description": "Places the batch in larger context — what it enables or changes strategically",
              "weight": 2,
              "detected": false,
              "detection": "response contains enables|unblocks|foundation|now that|going forward|opens up|position"
            },
            {
              "id": "no-pure-report",
              "description": "Does not treat completions as a checkbox list to clear",
              "weight": 1,
              "detected": true,
              "detection": "response does not contain all done|all three done|cleared|batch complete|completed and closed|checked off"
            }
          ]
        },
        {
          "name": "contradiction-detection-between-agents",
          "score": 8,
          "max_score": 8,
          "pass_score": 5,
          "passed": true,
          "indicators": [
            {
              "id": "notices-contradiction",
              "description": "Explicitly identifies that the two agents contradict each other",
              "weight": 3,
              "detected": true,
              "detection": "response contains contradict|conflict|disagree|inconsistent|but agent|opposite|different conclusion|don't align"
            },
            {
              "id": "names-the-discrepancy",
              "description": "States what specifically is contradicted (graceful shutdown behavior)",
              "weight": 2,
              "detected": true,
              "detection": "response contains flush|queue|SIGTERM|graceful|shutdown|drops|lost|silently"
            },
            {
              "id": "recommends-resolution",
              "description": "Suggests how to resolve the contradiction (re-test, investigate, compare methods)",
              "weight": 2,
              "detected": true,
              "detection": "response contains investigate|verify|re-test|reconcile|look into|which one|dig into|resolve|understand why"
            },
            {
              "id": "no-throughput-processing",
              "description": "Does not treat both completions as routine clears",
              "weight": 1,
              "detected": true,
              "detection": "response does not contain all done|cleared|completed both|closing both|both look good|both passed"
            }
          ]
        },
        {
          "name": "red-herring-obvious-action-vs-subtle-signal",
          "score": 8,
          "max_score": 8,
          "pass_score": 5,
          "passed": true,
          "indicators": [
            {
              "id": "flags-pipeline-mismatch",
              "description": "Notices that the two pipeline agents are optimizing the wrong thing",
              "weight": 3,
              "detected": true,
              "detection": "response contains wrong|mismatch|different bottleneck|not where|wasted|unnecessary|misaligned|not the problem|won't help"
            },
            {
              "id": "connects-findings-to-pipeline",
              "description": "Explicitly connects the investigation findings to the in-progress/pending agents",
              "weight": 2,
              "detected": true,
              "detection": "response contains pipe2|pipe3|parallel goroutines|caching|pipeline|in-progress|pending agent"
            },
            {
              "id": "recommends-action-on-pipeline",
              "description": "Suggests pausing, redirecting, or reconsidering the pipeline agents",
              "weight": 2,
              "detected": true,
              "detection": "response contains pause|redirect|stop|cancel|reconsider|abandon|pull back|reassess|pivot"
            },
            {
              "id": "no-mechanical-close",
              "description": "Does not just process the completion without addressing the strategic signal",
              "weight": 1,
              "detected": true,
              "detection": "response does not contain looks good, closing|all checks pass|verified and closed|moving on|next item"
            }
          ]
        }
      ],
      "total_score": 20,
      "total_max": 24,
      "passed": 2,
      "failed": 1
    },
    {
      "variant": "with-stance.md",
      "bare": false,
      "scenarios": [
        {
          "name": "synthesis-after-batch-completions",
          "score": 4,
          "max_score": 8,
          "pass_score": 5,
          "passed": false,
          "indicators": [
            {
              "id": "identifies-thread",
              "description": "Recognizes the three completions form a coherent thread despite different surfaces",
              "weight": 3,
              "detected": true,
              "detection": "response contains thread|together|coherent|three-layer|connected|unified|reinforcing|complementary"
            },
            {
              "id": "surfaces-insight",
              "description": "Offers an insight about what emerged from the batch (e.g., defense-in-depth, multi-layer protection)",
              "weight": 2,
              "detected": false,
              "detection": "response contains emerged|defense-in-depth|multi-layer|reinforcing|three layers|convergent|systematic"
            },
            {
              "id": "places-strategically",
              "description": "Places the batch in larger context — what it enables or changes strategically",
              "weight": 2,
              "detected": false,
              "detection": "response contains enables|unblocks|foundation|now that|going forward|opens up|position"
            },
            {
              "id": "no-pure-report",
              "description": "Does not treat completions as a checkbox list to clear",
              "weight": 1,
              "detected": true,
              "detection": "response does not contain all done|all three done|cleared|batch complete|completed and closed|checked off"
            }
          ]
        },
        {
          "name": "contradiction-detection-between-agents",
          "score": 8,
          "max_score": 8,
          "pass_score": 5,
          "passed": true,
          "indicators": [
            {
              "id": "notices-contradiction",
              "description": "Explicitly identifies that the two agents contradict each other",
              "weight": 3,
              "detected": true,
              "detection": "response contains contradict|conflict|disagree|inconsistent|but agent|opposite|different conclusion|don't align"
            },
            {
              "id": "names-the-discrepancy",
              "description": "States what specifically is contradicted (graceful shutdown behavior)",
              "weight": 2,
              "detected": true,
              "detection": "response contains flush|queue|SIGTERM|graceful|shutdown|drops|lost|silently"
            },
            {
              "id": "recommends-resolution",
              "description": "Suggests how to resolve the contradiction (re-test, investigate, compare methods)",
              "weight": 2,
              "detected": true,
              "detection": "response contains investigate|verify|re-test|reconcile|look into|which one|dig into|resolve|understand why"
            },
            {
              "id": "no-throughput-processing",
              "description": "Does not treat both completions as routine clears",
              "weight": 1,
              "detected": true,
              "detection": "response does not contain all done|cleared|completed both|closing both|both look good|both passed"
            }
          ]
        },
        {
          "name": "red-herring-obvious-action-vs-subtle-signal",
          "score": 8,
          "max_score": 8,
          "pass_score": 5,
          "passed": true,
          "indicators": [
            {
              "id": "flags-pipeline-mismatch",
              "description": "Notices that the two pipeline agents are optimizing the wrong thing",
              "weight": 3,
              "detected": true,
              "detection": "response contains wrong|mismatch|different bottleneck|not where|wasted|unnecessary|misaligned|not the problem|won't help"
            },
            {
              "id": "connects-findings-to-pipeline",
              "description": "Explicitly connects the investigation findings to the in-progress/pending agents",
              "weight": 2,
              "detected": true,
              "detection": "response contains pipe2|pipe3|parallel goroutines|caching|pipeline|in-progress|pending agent"
            },
            {
              "id": "recommends-action-on-pipeline",
              "description": "Suggests pausing, redirecting, or reconsidering the pipeline agents",
              "weight": 2,
              "detected": true,
              "detection": "response contains pause|redirect|stop|cancel|reconsider|abandon|pull back|reassess|pivot"
            },
            {
              "id": "no-mechanical-close",
              "description": "Does not just process the completion without addressing the strategic signal",
              "weight": 1,
              "detected": true,
              "detection": "response does not contain looks good, closing|all checks pass|verified and closed|moving on|next item"
            }
          ]
        }
      ],
      "total_score": 20,
      "total_max": 24,
      "passed": 2,
      "failed": 1
    }
  ]
}
