{
  "builds": [
    {
      "timestamp": "2025-12-25T20:45:12.128787-08:00",
      "total_tokens": 2872,
      "sources": {
        "feature-impl": 2872
      }
    },
    {
      "timestamp": "2025-12-25T21:55:07.1353-08:00",
      "total_tokens": 2981,
      "sources": {
        "feature-impl": 2981
      }
    },
    {
      "timestamp": "2025-12-25T21:56:34.25353-08:00",
      "total_tokens": 2981,
      "sources": {
        "feature-impl": 2981
      }
    },
    {
      "timestamp": "2025-12-27T19:04:53.385886-08:00",
      "total_tokens": 2984,
      "sources": {
        "feature-impl": 2984
      }
    },
    {
      "timestamp": "2025-12-30T10:08:50.978719-08:00",
      "total_tokens": 3205,
      "sources": {
        "feature-impl": 3205
      }
    },
    {
      "timestamp": "2025-12-30T10:09:41.004021-08:00",
      "total_tokens": 3283,
      "sources": {
        "feature-impl": 3283
      }
    },
    {
      "timestamp": "2026-01-07T14:41:54.675651-08:00",
      "total_tokens": 3560,
      "sources": {
        "feature-impl": 3560
      }
    },
    {
      "timestamp": "2026-01-08T16:43:11.795709-08:00",
      "total_tokens": 3744,
      "sources": {
        "feature-impl": 3744
      }
    },
    {
      "timestamp": "2026-01-16T11:00:03.447986-08:00",
      "total_tokens": 3744,
      "sources": {
        "feature-impl": 3744
      }
    },
    {
      "timestamp": "2026-01-16T11:00:19.749314-08:00",
      "total_tokens": 3744,
      "sources": {
        "feature-impl": 3744
      }
    },
    {
      "timestamp": "2026-01-19T10:40:31.216841-08:00",
      "total_tokens": 3778,
      "sources": {
        "feature-impl": 3778
      }
    },
    {
      "timestamp": "2026-02-03T17:38:11.751707-08:00",
      "total_tokens": 4822,
      "sources": {
        "feature-impl": 4822
      }
    },
    {
      "timestamp": "2026-02-11T13:57:18.831512-08:00",
      "total_tokens": 4822,
      "sources": {
        "feature-impl": 4822
      }
    },
    {
      "timestamp": "2026-02-11T13:59:40.879688-08:00",
      "total_tokens": 4830,
      "sources": {
        "feature-impl": 4830
      }
    },
    {
      "timestamp": "2026-02-25T18:05:02.044802-08:00",
      "total_tokens": 5110,
      "sources": {
        "feature-impl": 5110
      }
    },
    {
      "timestamp": "2026-03-03T10:47:22.005835-08:00",
      "total_tokens": 5105,
      "sources": {
        "feature-impl": 5105
      }
    },
    {
      "timestamp": "2026-03-06T16:43:47.778524-08:00",
      "total_tokens": 2128,
      "sources": {
        "feature-impl": 2128
      }
    }
  ]
}